LICENSE
setup.py
termlayout/__init__.py
termlayout/__main__.py
termlayout.egg-info/PKG-INFO
termlayout.egg-info/SOURCES.txt
termlayout.egg-info/dependency_links.txt
termlayout.egg-info/entry_points.txt
termlayout.egg-info/top_level.txt