Metadata-Version: 2.1
Name: termlayout
Version: 0.18
Summary: text-mode HTML formatter for Unix terminals, supports ruby, tables, wide characters etc
Home-page: http://ssb22.user.srcf.net/adjuster/termlayout.html
Author: Silas S. Brown
Author-email: ssb22@cam.ac.uk
License: Apache 2
Platform: any
Classifier: Programming Language :: Python :: 2
Classifier: Programming Language :: Python :: 3
Classifier: License :: OSI Approved :: Apache Software License
Classifier: Operating System :: OS Independent
Requires-Python: >=2.3
License-File: LICENSE
